{
  "buildSentences": [
    {
      "words": [
        "the",
        "researchers",
        "found",
        "that",
        "exercise",
        "improves",
        "mental",
        "health"
      ],
      "display": "The researchers found that exercise improves mental health."
    },
    {
      "words": [
        "students",
        "should",
        "not",
        "procrastinate",
        "their",
        "assignments",
        "to",
        "achieve"
      ],
      "display": "Students should not procrastinate their assignments to achieve."
    },
    {
      "words": [
        "the",
        "experiment",
        "results",
        "suggested",
        "that",
        "more",
        "study",
        "is",
        "required"
      ],
      "display": "The experiment results suggested that more study is required."
    },
    {
      "words": [
        "she",
        "enjoys",
        "reading",
        "books",
        "that",
        "challenge",
        "her",
        "thinking"
      ],
      "display": "She enjoys reading books that challenge her thinking."
    },
    {
      "words": [
        "environmental",
        "protection",
        "is",
        "important",
        "for",
        "future",
        "generations",
        "to"
      ],
      "display": "Environmental protection is important for future generations to."
    },
    {
      "words": [
        "the",
        "team",
        "worked",
        "hard",
        "to",
        "complete",
        "the",
        "project",
        "before",
        "the",
        "deadline"
      ],
      "display": "The team worked hard to complete the project before the deadline."
    },
    {
      "words": [
        "this",
        "study",
        "will",
        "provide",
        "insights",
        "into",
        "consumer",
        "behavior",
        "and",
        "trends"
      ],
      "display": "This study will provide insights into consumer behavior and trends."
    },
    {
      "words": [
        "the",
        "classroom",
        "environment",
        "can",
        "greatly",
        "affect",
        "students",
        "learning"
      ],
      "display": "The classroom environment can greatly affect students learning."
    }
  ],
  "emailPrompts": [
    "寄信給教授，詢問有關期末專題報告的要求和截止日期。",
    "寄信給宿舍辦公室，請求延長住宿合約的時間。",
    "寄信給圖書館，詢問借書的政策和罰款事宜。",
    "寄信給社團，表達對即將舉行的活動的興趣並詢問參加方式。",
    "寄信給客服部門，反映最近一次購物的問題並要求解決方案。",
    "寄信給導師，感謝他們對學習的幫助並詢問進一步的建議。"
  ],
  "discussionPrompts": [
    "教授問：「環保與經濟發展之間的關係應該如何平衡？」",
    "教授問：「科技進步對社會互動的影響是正面還是負面？」",
    "教授問：「大學教育應該重視實用技能還是理論知識？」",
    "教授問：「社會媒體對青少年的心理健康有什麼影響？」",
    "教授問：「應該如何應對全球暖化的挑戰？」",
    "教授問：「文化多樣性對社會的貢獻與挑戰是什麼？」"
  ]
}