{
  "buildSentences": [
    {
      "words": [
        "the",
        "research",
        "study",
        "on",
        "climate",
        "change",
        "has",
        "significant",
        "implications"
      ],
      "display": "The research study on climate change has significant implications."
    },
    {
      "words": [
        "students",
        "should",
        "be",
        "encouraged",
        "to",
        "participate",
        "in",
        "community",
        "service"
      ],
      "display": "Students should be encouraged to participate in community service."
    },
    {
      "words": [
        "the",
        "book",
        "you",
        "recommended",
        "was",
        "both",
        "informative",
        "and",
        "entertaining"
      ],
      "display": "The book you recommended was both informative and entertaining."
    },
    {
      "words": [
        "attending",
        "lectures",
        "regularly",
        "helps",
        "students",
        "understand",
        "the",
        "material",
        "better"
      ],
      "display": "Attending lectures regularly helps students understand the material better."
    },
    {
      "words": [
        "the",
        "team",
        "is",
        "working",
        "on",
        "developing",
        "a",
        "new",
        "software",
        "application"
      ],
      "display": "The team is working on developing a new software application."
    },
    {
      "words": [
        "it",
        "is",
        "important",
        "to",
        "analyze",
        "data",
        "before",
        "drawing",
        "conclusions"
      ],
      "display": "It is important to analyze data before drawing conclusions."
    },
    {
      "words": [
        "after",
        "finishing",
        "the",
        "project",
        "we",
        "will",
        "present",
        "our",
        "findings",
        "to",
        "the",
        "class"
      ],
      "display": "After finishing the project we will present our findings to the class."
    },
    {
      "words": [
        "the",
        "effects",
        "of",
        "social",
        "media",
        "on",
        "youth",
        "are",
        "still",
        "being",
        "studied"
      ],
      "display": "The effects of social media on youth are still being studied."
    }
  ],
  "emailPrompts": [
    "寄信給教授，要求延長提交論文的截止日期，因為遇到個人問題。",
    "寄信給宿舍管理辦公室，查詢房租的支付方式和截止日期。",
    "寄信給圖書館，詢問關於圖書館的開放時間和借書規則。",
    "寄信給學校社團，表達加入某個社團的興趣，並詢問相關活動。",
    "寄信給客服，反映最近購買的商品存在問題，要求退換貨。",
    "寄信給學術顧問，請教選課的建議和畢業要求。"
  ],
  "discussionPrompts": [
    "教授問：「在學習中，背景知識的重要性是什麼？」",
    "教授問：「社會媒體影響現代溝通的方式嗎？」",
    "教授問：「環境保護與經濟發展應該如何平衡？」",
    "教授問：「技術進步對於職場的影響有哪些？」",
    "教授問：「藝術在社會變遷中的角色是什麼？」",
    "教授問：「多元文化社會的優缺點有哪些？」"
  ]
}